odoo/addons/sale_timesheet_project_link/README.rst
odoo/addons/sale_timesheet_project_link/__init__.py
odoo/addons/sale_timesheet_project_link/__manifest__.py
odoo/addons/sale_timesheet_project_link/i18n/fr.po
odoo/addons/sale_timesheet_project_link/i18n/sale_timesheet_project_link.pot
odoo/addons/sale_timesheet_project_link/models/__init__.py
odoo/addons/sale_timesheet_project_link/models/sale_order.py
odoo/addons/sale_timesheet_project_link/static/description/icon.png
odoo/addons/sale_timesheet_project_link/tests/__init__.py
odoo/addons/sale_timesheet_project_link/tests/test_sale_timesheet_project_link.py
odoo/addons/sale_timesheet_project_link/views/sale_order.xml
odoo11_addon_sale_timesheet_project_link-11.0.1.0.1.dist-info/METADATA
odoo11_addon_sale_timesheet_project_link-11.0.1.0.1.dist-info/WHEEL
odoo11_addon_sale_timesheet_project_link-11.0.1.0.1.dist-info/top_level.txt
odoo11_addon_sale_timesheet_project_link-11.0.1.0.1.dist-info/RECORD
